unknownannei/__init__.py
unknownannei/unknownannei.py
unknownannei-1.5.dist-info/LICENSE
unknownannei-1.5.dist-info/METADATA
unknownannei-1.5.dist-info/WHEEL
unknownannei-1.5.dist-info/top_level.txt
unknownannei-1.5.dist-info/RECORD
